tree_sitter_hygen_template-0.5.0.dist-info/RECORD
tree_sitter_hygen_template-0.5.0.dist-info/WHEEL
tree_sitter_hygen_template-0.5.0.dist-info/top_level.txt
tree_sitter_hygen_template-0.5.0.dist-info/METADATA
tree_sitter_hygen_template-0.5.0.dist-info/licenses/LICENSE
tree_sitter_hygen_template/__init__.pyi
tree_sitter_hygen_template/binding.c
tree_sitter_hygen_template/__init__.py
tree_sitter_hygen_template/py.typed
tree_sitter_hygen_template/_binding.abi3.so
tree_sitter_hygen_template/queries/highlights.scm
tree_sitter_hygen_template/queries/injections.scm
