Metadata-Version: 2.4
Name: tree-sitter-hygen-template
Version: 0.5.0
Summary: Hygen Template grammar for tree-sitter
Author-email: Héctor Ochoa <hector.ochoa.dev@gmail.com>
License: MIT
Project-URL: Homepage, https://github.com/Hdoc1509/tree-sitter-hygen-template
Keywords: incremental,parsing,tree-sitter,hygen-template
Classifier: Intended Audience :: Developers
Classifier: License :: OSI Approved :: MIT License
Classifier: Topic :: Software Development :: Compilers
Classifier: Topic :: Text Processing :: Linguistic
Classifier: Typing :: Typed
Requires-Python: >=3.9
License-File: LICENSE
Provides-Extra: core
Requires-Dist: tree-sitter~=0.22; extra == "core"
Dynamic: license-file
